COPYING
INSTALL.txt
MANIFEST.in
README.txt
setup.py
hwit/__init__.py
hwit/examples/__init__.py
hwit/examples/about.py
hwit/examples/common/__init__.py
hwit/examples/common/actor.hwit
hwit/examples/common/agent-g3-blank.hwit
hwit/examples/common/agent-g3-blank.tsv
hwit/examples/common/agent-g3-notitle.hwit
hwit/examples/common/agent_a.cfg
hwit/examples/common/agent_b.cfg
hwit/examples/common/agent_c.cfg
hwit/examples/common/attitude_form.hwit
hwit/examples/common/attitude_form.tsv
hwit/examples/common/basic.hwit
hwit/examples/common/blank.hwit
hwit/examples/common/corrugation-3003.hwit
hwit/examples/common/empty.hwit
hwit/examples/common/gui_test-template.tsv
hwit/examples/common/hwit-partial.hwit
hwit/examples/common/hwit_poll.hwit
hwit/examples/common/mobilisation.hwit
hwit/examples/common/mobilisation.tsv
hwit/examples/common/osvaldo-3915.hwit
hwit/examples/common/previsit.hwit
hwit/examples/common/risky.hwit
hwit/examples/common/scout_camp.hwit
hwit/examples/common/scout_camp.tsv
hwit/examples/common/small.hwit
hwit/examples/common/spec.hwit
hwit/examples/common/underskirts-3915.hwit
hwit/examples/doc/Makefile
hwit/examples/doc/__init__.py
hwit/examples/doc/conf.py
hwit/examples/doc/index.rst
hwit/examples/doc/make.bat
hwit/examples/doc/_static/hwit_icon-96x96.png
hwit_examples.egg-info/PKG-INFO
hwit_examples.egg-info/SOURCES.txt
hwit_examples.egg-info/dependency_links.txt
hwit_examples.egg-info/entry_points.txt
hwit_examples.egg-info/namespace_packages.txt
hwit_examples.egg-info/top_level.txt