Metadata-Version: 1.1
Name: hwit-examples
Version: 0.01-r00018
Summary: Examples for use with HWIT
Home-page: http://hwit.org
Author: D Haynes
Author-email: tundish@thuswise.org
License: COPYING
Platform: UNKNOWN
Classifier: Operating System :: OS Independent
Classifier: Programming Language :: Python :: 2.7
Classifier: License :: OSI Approved :: GNU General Public License v3 or later (GPLv3+)
